swagger_client/__init__.py
swagger_client/api_client.py
swagger_client/configuration.py
swagger_client/main.py
swagger_client/rest.py
swagger_client/api/__init__.py
swagger_client/api/auth_api.py
swagger_client/api/health_api.py
swagger_client/api/orders_api.py
swagger_client/api/products_api.py
swagger_client/api/shops_api.py
swagger_client/api/supplier_api.py
swagger_client/models/__init__.py
swagger_client/models/api_response_authentication_response.py
swagger_client/models/api_response_get_shop_response.py
swagger_client/models/api_response_list_cancel_option_response.py
swagger_client/models/api_response_list_order_response.py
swagger_client/models/api_response_object.py
swagger_client/models/api_response_order_report_response.py
swagger_client/models/api_response_order_report_response_wrapper.py
swagger_client/models/api_response_pageable_response_shop_products_response.py
swagger_client/models/api_response_pageable_response_shop_products_response_data.py
swagger_client/models/api_response_price_and_quantity_batch_response.py
swagger_client/models/api_response_price_and_quantity_batch_response_wrapper.py
swagger_client/models/api_response_product_batch_ticket_response.py
swagger_client/models/api_response_shop_couriers_working_status_response.py
swagger_client/models/api_response_shop_working_hours_response.py
swagger_client/models/api_response_void.py
swagger_client/models/artisan_order_response.py
swagger_client/models/authentication_response.py
swagger_client/models/cancel_option_response.py
swagger_client/models/cancel_order_request.py
swagger_client/models/customer_response.py
swagger_client/models/field_validation.py
swagger_client/models/general_error.py
swagger_client/models/general_error_wrapper.py
swagger_client/models/get_shop_response.py
swagger_client/models/health_response.py
swagger_client/models/internal_error.py
swagger_client/models/internal_error_wrapper.py
swagger_client/models/invoice_address_response.py
swagger_client_sameterayerdem-1.0.0.dist-info/METADATA
swagger_client_sameterayerdem-1.0.0.dist-info/WHEEL
swagger_client_sameterayerdem-1.0.0.dist-info/top_level.txt
swagger_client_sameterayerdem-1.0.0.dist-info/RECORD
